haystack_pydantic/__init__.py
haystack_pydantic/core/component/__init__.py
haystack_pydantic/core/component/component.py
haystack_pydantic/core/pipeline/pipeline.py
haystack_pydantic/py.typed
haystack_pydantic-0.1.0.dist-info/METADATA
haystack_pydantic-0.1.0.dist-info/WHEEL
haystack_pydantic-0.1.0.dist-info/RECORD
