Metadata-Version: 2.3
Name: haystack-pydantic
Version: 0.1.0
Summary: Define haystack components with pydantic models
Author: Satoshi
Author-email: 6world4trigger@gmail.com
Requires-Python: >=3.9,<3.13
Classifier: Programming Language :: Python :: 3
Classifier: Programming Language :: Python :: 3.9
Classifier: Programming Language :: Python :: 3.10
Classifier: Programming Language :: Python :: 3.11
Classifier: Programming Language :: Python :: 3.12
Requires-Dist: haystack-ai (>=2.9.0,<3.0.0)
Requires-Dist: pydantic (>=2.10.5,<3.0.0)
